{
    "frames": [
        {
            "filename": "idle_down_1",
            "frame": {
                "w": 32,
                "h": 32,
                "x": 0,
                "y": 0
            },
            "anchor": {
                "x": 0.5,
                "y": 0.5
            }
        },
        {
            "filename": "idle_down_2",
            "frame": {
                "w": 32,
                "h": 32,
                "x": 32,
                "y": 0
            },
            "anchor": {
                "x": 0.5,
                "y": 0.5
            }
        },
        {
            "filename": "idle_down_3",
            "frame": {
                "w": 32,
                "h": 32,
                "x": 64,
                "y": 0
            },
            "anchor": {
                "x": 0.5,
                "y": 0.5
            }
        },
        {
            "filename": "idle_down_4",
            "frame": {
                "w": 32,
                "h": 32,
                "x": 96,
                "y": 0
            },
            "anchor": {
                "x": 0.5,
                "y": 0.5
            }
        },
        {
            "filename": "idle_up_1",
            "frame": {
                "w": 32,
                "h": 32,
                "x": 0,
                "y": 32
            },
            "anchor": {
                "x": 0.5,
                "y": 0.5
            }
        },
        {
            "filename": "idle_up_2",
            "frame": {
                "w": 32,
                "h": 32,
                "x": 32,
                "y": 32
            },
            "anchor": {
                "x": 0.5,
                "y": 0.5
            }
        },
        {
            "filename": "idle_up_3",
            "frame": {
                "w": 32,
                "h": 32,
                "x": 64,
                "y": 32
            },
            "anchor": {
                "x": 0.5,
                "y": 0.5
            }
        },
        {
            "filename": "idle_up_4",
            "frame": {
                "w": 32,
                "h": 32,
                "x": 96,
                "y": 32
            },
            "anchor": {
                "x": 0.5,
                "y": 0.5
            }
        },
        {
            "filename": "idle_right_1",
            "frame": {
                "w": 32,
                "h": 32,
                "x": 0,
                "y": 64
            },
            "anchor": {
                "x": 0.5,
                "y": 0.5
            }
        },
        {
            "filename": "idle_right_2",
            "frame": {
                "w": 32,
                "h": 32,
                "x": 32,
                "y": 64
            },
            "anchor": {
                "x": 0.5,
                "y": 0.5
            }
        },
        {
            "filename": "idle_right_3",
            "frame": {
                "w": 32,
                "h": 32,
                "x": 64,
                "y": 64
            },
            "anchor": {
                "x": 0.5,
                "y": 0.5
            }
        },
        {
            "filename": "idle_right_4",
            "frame": {
                "w": 32,
                "h": 32,
                "x": 96,
                "y": 64
            },
            "anchor": {
                "x": 0.5,
                "y": 0.5
            }
        },
        {
            "filename": "run_down_1",
            "frame": {
                "w": 32,
                "h": 32,
                "x": 0,
                "y": 96
            },
            "anchor": {
                "x": 0.5,
                "y": 0.5
            }
        },
        {
            "filename": "run_down_2",
            "frame": {
                "w": 32,
                "h": 32,
                "x": 32,
                "y": 96
            },
            "anchor": {
                "x": 0.5,
                "y": 0.5
            }
        },
        {
            "filename": "run_down_3",
            "frame": {
                "w": 32,
                "h": 32,
                "x": 64,
                "y": 96
            },
            "anchor": {
                "x": 0.5,
                "y": 0.5
            }
        },
        {
            "filename": "run_down_4",
            "frame": {
                "w": 32,
                "h": 32,
                "x": 96,
                "y": 96
            },
            "anchor": {
                "x": 0.5,
                "y": 0.5
            }
        },
        {
            "filename": "run_up_1",
            "frame": {
                "w": 32,
                "h": 32,
                "x": 0,
                "y": 128
            },
            "anchor": {
                "x": 0.5,
                "y": 0.5
            }
        },
        {
            "filename": "run_up_2",
            "frame": {
                "w": 32,
                "h": 32,
                "x": 32,
                "y": 128
            },
            "anchor": {
                "x": 0.5,
                "y": 0.5
            }
        },
        {
            "filename": "run_up_3",
            "frame": {
                "w": 32,
                "h": 32,
                "x": 64,
                "y": 128
            },
            "anchor": {
                "x": 0.5,
                "y": 0.5
            }
        },
        {
            "filename": "run_up_4",
            "frame": {
                "w": 32,
                "h": 32,
                "x": 96,
                "y": 128
            },
            "anchor": {
                "x": 0.5,
                "y": 0.5
            }
        },
        {
            "filename": "run_right_1",
            "frame": {
                "w": 32,
                "h": 32,
                "x": 0,
                "y": 160
            },
            "anchor": {
                "x": 0.5,
                "y": 0.5
            }
        },
        {
            "filename": "run_right_2",
            "frame": {
                "w": 32,
                "h": 32,
                "x": 32,
                "y": 160
            },
            "anchor": {
                "x": 0.5,
                "y": 0.5
            }
        },
        {
            "filename": "run_right_3",
            "frame": {
                "w": 32,
                "h": 32,
                "x": 64,
                "y": 160
            },
            "anchor": {
                "x": 0.5,
                "y": 0.5
            }
        },
        {
            "filename": "run_right_4",
            "frame": {
                "w": 32,
                "h": 32,
                "x": 96,
                "y": 160
            },
            "anchor": {
                "x": 0.5,
                "y": 0.5
            }
        }
    ],
    "meta": {
        "description": "Atlas generado con Atlas Packer Gamma V2",
        "web": "https://gammafp.github.io/atlas-packer-phaser/"
    }
}